metaflow_extensions/corise/__init__.py
metaflow_extensions/corise/plugins/cards/corise/__init__.py
metaflow_extensions/corise/plugins/cards/corise/base.html
metaflow_extensions/corise/plugins/cards/corise/bundle.css
metaflow_extensions/corise/plugins/cards/corise/main.js
metaflow_card_corise-1.0.1.dist-info/LICENSE
metaflow_card_corise-1.0.1.dist-info/METADATA
metaflow_card_corise-1.0.1.dist-info/WHEEL
metaflow_card_corise-1.0.1.dist-info/top_level.txt
metaflow_card_corise-1.0.1.dist-info/RECORD
